aityz_chess/__init__.py
aityz_chess/cache.py
aityz_chess/types.py
aityz_chess/analysis/__init__.py
aityz_chess/stockfish/__init__.py
aityz_chess-1.1.4.dist-info/METADATA
aityz_chess-1.1.4.dist-info/WHEEL
aityz_chess-1.1.4.dist-info/top_level.txt
aityz_chess-1.1.4.dist-info/RECORD
